linora/__init__.py
linora/audio/__init__.py
linora/audio/_audio_io.py
linora/audio/_audio_util.py
linora/chart/__init__.py
linora/chart/_arrow.py
linora/chart/_bar.py
linora/chart/_base.py
linora/chart/_boxplot.py
linora/chart/_circle.py
linora/chart/_coherence.py
linora/chart/_config.py
linora/chart/_csd.py
linora/chart/_ellipse.py
linora/chart/_errorbar.py
linora/chart/_feature.py
linora/chart/_fillline.py
linora/chart/_grid.py
linora/chart/_hist.py
linora/chart/_hist2d.py
linora/chart/_hlines.py
linora/chart/_line.py
linora/chart/_line3D.py
linora/chart/_metrics.py
linora/chart/_pie.py
linora/chart/_plot.py
linora/chart/_polygon.py
linora/chart/_radar.py
linora/chart/_rectangle.py
linora/chart/_regularpolygon.py
linora/chart/_scatter.py
linora/chart/_scatter3D.py
linora/chart/_vlines.py
linora/chart/_wedge.py
linora/data/__init__.py
linora/data/_compress.py
linora/data/_sql_io_dataset.py
linora/data/_utils.py
linora/data/Dataset/__init__.py
linora/data/Dataset/_data.py
linora/data/Dataset/_dataset.py
linora/data/TextLineDataset/__init__.py
linora/data/TextLineDataset/_dataset.py
linora/data/datasets/__init__.py
linora/data/datasets/_config_path.py
linora/data/datasets/_mnist.py
linora/data/datasets/_utils.py
linora/data/datasets/_weather.py
linora/feature_column/__init__.py
linora/feature_column/_categorical.py
linora/feature_column/_feature.py
linora/feature_column/_normalize.py
linora/feature_column/_numerical.py
linora/feature_column/boundary/__init__.py
linora/feature_column/boundary/_boundary.py
linora/feature_selection/__init__.py
linora/feature_selection/_credit.py
linora/feature_selection/_select.py
linora/gfile/__init__.py
linora/gfile/_gfile.py
linora/image/__init__.py
linora/image/_image_aug.py
linora/image/_image_box.py
linora/image/_image_color.py
linora/image/_image_color_aug.py
linora/image/_image_crop.py
linora/image/_image_crop_aug.py
linora/image/_image_draw.py
linora/image/_image_draw_aug.py
linora/image/_image_feature.py
linora-1.6.0.dist-info/LICENSE.txt
linora-1.6.0.dist-info/METADATA
linora-1.6.0.dist-info/WHEEL
linora-1.6.0.dist-info/top_level.txt
linora-1.6.0.dist-info/RECORD
