Metadata-Version: 2.1
Name: linora
Version: 1.6.0
Summary: Simple and efficient tools for data mining and data analysis.
Home-page: https://github.com/Hourout/linora
Author: JinQing Lee
Author-email: hourout@163.com
License: Apache License Version 2.0
Keywords: hyperparameter-optimization,XGBoost,LightGBM,data-mining,data-analysis,machine-learning,image,text,data-science,logging,parallel,feature-engineering,metrics,schedulers,datasets
Platform: UNKNOWN
Classifier: Intended Audience :: Developers
Classifier: Intended Audience :: Education
Classifier: Intended Audience :: Science/Research
Classifier: Topic :: Scientific/Engineering
Classifier: Topic :: Scientific/Engineering :: Artificial Intelligence
Classifier: Topic :: Scientific/Engineering :: Visualization
Classifier: License :: OSI Approved :: Apache Software License
Classifier: Programming Language :: Python :: 3.8
Classifier: Programming Language :: Python :: 3.9
Classifier: Programming Language :: Python :: 3.10
Classifier: Programming Language :: Python :: 3.11
Requires-Dist: pandas (>=1.5.2)
Requires-Dist: Pillow (>=9.3.0)
Requires-Dist: joblib (>=1.2.0)
Requires-Dist: requests (>=2.28.0)
Requires-Dist: rarfile
